MANIFEST.in
README.md
setup.py
bin/chamberconnectlibrary-test.py
chamberconnectlibrary/__init__.py
chamberconnectlibrary/controllerinterface.py
chamberconnectlibrary/espec.py
chamberconnectlibrary/especinteract.py
chamberconnectlibrary/modbus.py
chamberconnectlibrary/p300.py
chamberconnectlibrary/p300debug.py
chamberconnectlibrary/scp220.py
chamberconnectlibrary/scp220debug.py
chamberconnectlibrary/watlowf4.py
chamberconnectlibrary/watlowf4t.py
chamberconnectlibrary.egg-info/PKG-INFO
chamberconnectlibrary.egg-info/SOURCES.txt
chamberconnectlibrary.egg-info/dependency_links.txt
chamberconnectlibrary.egg-info/not-zip-safe
chamberconnectlibrary.egg-info/pbr.json
chamberconnectlibrary.egg-info/requires.txt
chamberconnectlibrary.egg-info/top_level.txt