Metadata-Version: 1.0
Name: chamberconnectlibrary
Version: 2.2.5
Summary: A library for interfacing with Espec North America chambers
Home-page: https://github.com/EspecNorthAmerica/ChamberConnectLibrary
Author: Espec North America
Author-email: mmetzler@espec.com
License: MIT
Keywords: Espec P300 SCP220 F4T F4
Platform: UNKNOWN
